seaice3p/__init__.py
seaice3p/__main__.py
seaice3p/diagnostics/__init__.py
seaice3p/diagnostics/brine_drainage_parameterisation.py
seaice3p/enthalpy_method/__init__.py
seaice3p/enthalpy_method/common.py
seaice3p/enthalpy_method/enthalpy_method.py
seaice3p/enthalpy_method/gas.py
seaice3p/enthalpy_method/phase_boundaries.py
seaice3p/equations/RJW14/__init__.py
seaice3p/equations/RJW14/brine_channel_sink_terms.py
seaice3p/equations/RJW14/brine_drainage.py
seaice3p/equations/__init__.py
seaice3p/equations/equations.py
seaice3p/equations/flux/__init__.py
seaice3p/equations/flux/bulk_dissolved_gas_flux.py
seaice3p/equations/flux/bulk_gas_flux.py
seaice3p/equations/flux/gas_fraction_flux.py
seaice3p/equations/flux/heat_flux.py
seaice3p/equations/flux/salt_flux.py
seaice3p/equations/nucleation.py
seaice3p/equations/radiative_heating.py
seaice3p/equations/velocities/__init__.py
seaice3p/equations/velocities/bubble_parameters.py
seaice3p/equations/velocities/mono_distribution.py
seaice3p/equations/velocities/power_law_distribution.py
seaice3p/equations/velocities/velocities.py
seaice3p/example.py
seaice3p/forcing/__init__.py
seaice3p/forcing/boundary_conditions.py
seaice3p/forcing/radiative_forcing.py
seaice3p/forcing/surface_energy_balance/__init__.py
seaice3p/forcing/surface_energy_balance/surface_energy_balance.py
seaice3p/forcing/surface_energy_balance/turbulent_heat_flux.py
seaice3p/forcing/temperature_forcing.py
seaice3p/forcing_data/BRW09.txt
seaice3p/forcing_data/BRW09_MBS_metadata.txt
seaice3p/grids.py
seaice3p/initial_conditions.py
seaice3p/load.py
seaice3p/oil_mass.py
seaice3p/params/__init__.py
seaice3p/params/bubble.py
seaice3p/params/convection.py
seaice3p/params/convert.py
seaice3p/params/dimensional/__init__.py
seaice3p/params/dimensional/bubble.py
seaice3p/params/dimensional/convection.py
seaice3p/params/dimensional/dimensional.py
seaice3p/params/dimensional/forcing.py
seaice3p/params/dimensional/gas.py
seaice3p/params/dimensional/initial_conditions.py
seaice3p-1.0.0.dist-info/METADATA
seaice3p-1.0.0.dist-info/WHEEL
seaice3p-1.0.0.dist-info/RECORD
