Metadata-Version: 2.1
Name: seaice3p
Version: 1.0.0
Summary: Simulate gas bubbles and oil droplets in sea ice.
License: MIT
Author: Joseph Fishlock
Author-email: joseph.fishlock@physics.ox.ax.uk
Requires-Python: >=3.12,<4.0
Classifier: License :: OSI Approved :: MIT License
Classifier: Programming Language :: Python :: 3
Classifier: Programming Language :: Python :: 3.12
Requires-Dist: matplotlib (>=3.9.2,<4.0.0)
Requires-Dist: metpy (>=1.6.3,<2.0.0)
Requires-Dist: netcdf4 (>=1.7.2,<2.0.0)
Requires-Dist: numpy (>=2.1.0,<3.0.0)
Requires-Dist: oilrad (==2.0.2)
Requires-Dist: pyserde[yaml] (>=0.22.0,<0.23.0)
Requires-Dist: scipy (>=1.14.0,<2.0.0)
Requires-Dist: xarray (>=2024.10.0,<2025.0.0)
